LICENSE
MANIFEST.in
README.md
meson.build
pyproject.toml
setup.py
Cyantities.egg-info/PKG-INFO
Cyantities.egg-info/SOURCES.txt
Cyantities.egg-info/dependency_links.txt
Cyantities.egg-info/entry_points.txt
Cyantities.egg-info/requires.txt
Cyantities.egg-info/top_level.txt
cyantities/__init__.py
cyantities/errors.py
cyantities/include.py
cyantities/quantity.pxd
cyantities/quantity.pyi
cyantities/quantity.pyx
cyantities/unit.pxd
cyantities/unit.pyi
cyantities/unit.pyx
cyantities/_cpp/cyantities/__init__.py
cyantities/_cpp/cyantities/boost.hpp
cyantities/_cpp/cyantities/quantitywrap.hpp
cyantities/_cpp/cyantities/unit.hpp
cyantities/_cpp/src/quantitywrap.cpp
cyantities/_cpp/src/test.cpp
cyantities/_cpp/src/unit.cpp
cyantities/scripts/__init__.py
cyantities/scripts/include.py
cyantities/scripts/link.py
examples/parabola/build.py
examples/parabola/meson.build
examples/parabola/parasolve.cpp
examples/parabola/parasolve.hpp
examples/parabola/parasolve.pyx
examples/parabola/run.py
examples/parabola/subprojects/cyantities/meson.build