Metadata-Version: 2.4
Name: Cyantities
Version: 0.6.0
Summary: Physical quantities with units.
Author-email: "Malte J. Ziebarth" <mjz.science@fmvkb.de>
License:                       EUROPEAN UNION PUBLIC LICENCE v. 1.2
Project-URL: Homepage, https://github.com/mjziebarth/Cyantities
Project-URL: Bug Tracker, https://github.com/mjziebarth/Cyantities/issues
Project-URL: Documentation, https://github.com/mjziebarth/Cyantities
Classifier: Development Status :: 2 - Pre-Alpha
Classifier: Programming Language :: Python :: 3
Classifier: Programming Language :: Cython
Classifier: Programming Language :: C++
Classifier: Intended Audience :: Science/Research
Classifier: Natural Language :: English
Classifier: Operating System :: POSIX :: Linux
License-File: LICENSE
Requires-Dist: numpy
Requires-Dist: cython
Requires-Dist: mebuex
Dynamic: license-file
